LBVH.cpython-310-x86_64-linux-gnu.so
lbvh-0.0.13.dist-info/WHEEL
lbvh-0.0.13.dist-info/RECORD
lbvh-0.0.13.dist-info/entry_points.txt
lbvh-0.0.13.dist-info/METADATA
lbvh-0.0.13.dist-info/licenses/LICENSE
