Metadata-Version: 2.1
Name: lbvh
Version: 0.0.13
Summary: A small bounding volume hierarchy implementation
Author-Email: Sam Mish <samuelpmish@gmail.com>
Classifier: Programming Language :: Python :: 3
Classifier: License :: OSI Approved :: MIT License
Classifier: Operating System :: OS Independent
Project-URL: Homepage, https://github.com/samuelpmish/LBVH
Project-URL: Bug tracker, https://github.com/samuelpmish/LBVH/issues
Requires-Python: >=3.8
